vulcan_core/__init__.py
vulcan_core/actions.py
vulcan_core/ast_utils.py
vulcan_core/conditions.py
vulcan_core/engine.py
vulcan_core/models.py
vulcan_core/reporting.py
vulcan_core/util.py
vulcan_core-1.2.0.dist-info/LICENSE
vulcan_core-1.2.0.dist-info/METADATA
vulcan_core-1.2.0.dist-info/NOTICE
vulcan_core-1.2.0.dist-info/WHEEL
vulcan_core-1.2.0.dist-info/RECORD
