Metadata-Version: 2.3
Name: vulcan-core
Version: 1.2.0
Summary: AI-Hybrid Rules Engine for Logical Reasoning.
License: Apache-2.0
Keywords: rules,logic,reasoning,ai,artificial intelligence,RAG,LLM
Requires-Python: >=3.12,<4.0
Classifier: License :: OSI Approved :: Apache Software License
Classifier: Operating System :: OS Independent
Classifier: Programming Language :: Python :: 3
Classifier: Programming Language :: Python :: 3.12
Classifier: Programming Language :: Python :: 3.13
Classifier: Topic :: Scientific/Engineering :: Artificial Intelligence
Classifier: Topic :: Software Development :: Libraries :: Python Modules
Provides-Extra: openai
Requires-Dist: langchain ; extra == "openai"
Requires-Dist: langchain-openai ; extra == "openai"
Requires-Dist: pydantic (>=2.11.7,<3.0.0)
Requires-Dist: pyyaml (>=6.0.2,<7.0.0)
Project-URL: Documentation, https://latchfield.com/vulcan/docs
Project-URL: Homepage, https://latchfield.com/vulcan
Project-URL: Repository, https://github.com/latchfield/vulcan-core
